{
  "feature_cols": [
    "Pregnancies",
    "Glucose",
    "BloodPressure",
    "SkinThickness",
    "Insulin",
    "BMI",
    "DiabetesPedigreeFunction",
    "Age"
  ],
  "loinc_map": {
    "Glucose": "2339-0",
    "BloodPressure": "55284-4",
    "BMI": "39156-5",
    "Insulin": "14749-6",
    "Age": "21612-7",
    "Pregnancies": "11996-6",
    "SkinThickness": "39106-0",
    "DiabetesPedigreeFunction": "33914-3"
  },
  "metrics": {
    "f1": 0.74,
    "auc_roc": 0.8612,
    "precision": 0.6167,
    "recall": 0.925,
    "threshold": 0.37,
    "n_train": 652,
    "n_val": 163,
    "n_test": 116
  },
  "decision_threshold": 0.37,
  "model_type": "xgboost",
  "thresholds": {
    "LOW": [
      0.0,
      0.3
    ],
    "MEDIUM": [
      0.3,
      0.6
    ],
    "HIGH": [
      0.6,
      0.85
    ],
    "CRITICAL": [
      0.85,
      1.0
    ]
  }
}